spclone/__init__.py
spclone/cli.py
spclone/clone_.py
spclone/tests/__init__.py
spclone/tests/conftest.py
spclone/tests/test_cli.py
spclone/tests/test_cli_edge_cases.py
spclone/tests/test_install.py
spclone-0.1.16.dist-info/licenses/LICENSE
spclone-0.1.16.dist-info/METADATA
spclone-0.1.16.dist-info/WHEEL
spclone-0.1.16.dist-info/entry_points.txt
spclone-0.1.16.dist-info/top_level.txt
spclone-0.1.16.dist-info/RECORD
