Metadata-Version: 2.4
Name: spclone
Version: 0.1.16
Summary: A lightweight alternative to 'git clone' for installing Python packages directly from GitHub.
Author-email: Sermet Pekin <Sermet.Pekin@gmail.com>
License: BSD 3-Clause License
Project-URL: Repository, https://github.com/SermetPekin/spclone
Project-URL: Homepage, https://github.com/SermetPekin/spclone
Project-URL: Documentation, https://github.com/SermetPekin/spclone
Project-URL: Issues, https://github.com/SermetPekin/spclone/issues
Project-URL: Changelog, https://github.com/SermetPekin/spclone/releases
Requires-Python: >=3.10
License-File: LICENSE
Requires-Dist: requests>=2.32.4
Dynamic: license-file
